CHANGELOG
COPYING
MANIFEST.in
README.rst
setup.cfg
setup.py
Hackersh.egg-info/PKG-INFO
Hackersh.egg-info/SOURCES.txt
Hackersh.egg-info/dependency_links.txt
Hackersh.egg-info/not-zip-safe
Hackersh.egg-info/requires.txt
Hackersh.egg-info/top_level.txt
bin/hackersh
hackersh/__init__.py
hackersh/_ordereddict.py
hackersh/_version.py
hackersh/conio.py
hackersh/exceptions.py
hackersh/log.py
hackersh/miscellaneous.py
hackersh/objects.py
hackersh/components/__init__.py
hackersh/components/external/__init__.py
hackersh/components/external/amap.py
hackersh/components/external/dnsdict6.py
hackersh/components/external/nbtscan.py
hackersh/components/external/nikto.py
hackersh/components/external/nmap.py
hackersh/components/external/ping.py
hackersh/components/external/sqlmap.py
hackersh/components/external/w3af.py
hackersh/components/external/xprobe2.py
hackersh/components/internal/__init__.py
hackersh/components/internal/browse.py
hackersh/components/internal/domain.py
hackersh/components/internal/hostname.py
hackersh/components/internal/ipv4_address.py
hackersh/components/internal/ipv4_range.py
hackersh/components/internal/ipv6_address.py
hackersh/components/internal/iterate_links.py
hackersh/components/internal/nslookup.py
hackersh/components/internal/submit.py
hackersh/components/internal/url.py
hackersh/components/system/__init__.py
hackersh/components/system/alert.py
hackersh/components/system/null.py
hackersh/components/system/print.py
hackersh/components/system/system.py
hackersh/components/system/tmpfile.py