Metadata-Version: 1.0
Name: Hackersh
Version: 0.2.0
Summary: Hacker Shell, a shell (command interpreter) written in Python with Pythonect-like syntax, built-in security commands, and out of the box wrappers for various security tools.
Home-page: http://www.hackersh.org/
Author: Itzik Kotler
Author-email: xorninja@gmail.com
License: GPLv2+
Platform: UNKNOWN
Classifier: Development Status :: 4 - Beta
Classifier: License :: OSI Approved :: GNU General Public License v2 or later (GPLv2+)
Classifier: Operating System :: OS Independent
Classifier: Programming Language :: Python
Classifier: Programming Language :: Python :: 2.6
Classifier: Programming Language :: Python :: 2.7
